{
"type": "FeatureCollection",
"features": [
{ "type": "Feature", "properties": { "Name": "Geschichtsstation 01: Altstadt", "lat": "51.4515", "lon": "6.6263", "Link": "http:\/\/www.moers.de\/C1257C84004E794D\/html\/D86AFE961CA4B001C1257CAE0047900B?OpenDocument&nocache=1" }, "geometry": { "type": "Point", "coordinates": [ 6.6263, 51.4515 ] } },
{ "type": "Feature", "properties": { "Name": "Denkmaltafel 02: Löwenapotheke", "lat": "51.4515", "lon": "6.6261", "Link": "http:\/\/www.moers.de\/C1257C84004E794D\/html\/401E686FBCBAA0D8C1257CAE004E48BE?OpenDocument&nocache=1" }, "geometry": { "type": "Point", "coordinates": [ 6.6261, 51.4515 ] } },
{ "type": "Feature", "properties": { "Name": "Geschichtstation 03: Evangelische Stadtkirche", "lat": "51.4511", "lon": "6.6256", "Link": "http:\/\/www.moers.de\/C1257C84004E794D\/html\/44AFA24742FABDD2C1257CAF0035822F?OpenDocument&nocache=1" }, "geometry": { "type": "Point", "coordinates": [ 6.6256, 51.4511 ] } },
{ "type": "Feature", "properties": { "Name": "Geschichtsstation 04: Schloss", "lat": "51.4497", "lon": "6.6245", "Link": "http:\/\/www.moers.de\/C1257C84004E794D\/html\/7F35E3B46DF4ABDBC1257CB3002C6734?OpenDocument&nocache=1" }, "geometry": { "type": "Point", "coordinates": [ 6.6245, 51.4497 ] } },
{ "type": "Feature", "properties": { "Name": "Geschichtsstation 05: Katholische Kirchen", "lat": "51.4496", "lon": "6.6252", "Link": "http:\/\/www.moers.de\/C1257C84004E794D\/html\/BDAD20886E8B2FD0C1257CB50025B432?OpenDocument&nocache=1" }, "geometry": { "type": "Point", "coordinates": [ 6.6252, 51.4496 ] } },
{ "type": "Feature", "properties": { "Name": "Geschichtsstation 06: Moers als Festungsstadt I", "lat": "51.4495", "lon": "6.6222", "Link": "http:\/\/www.moers.de\/C1257C84004E794D\/html\/CF8AF069362B1348C1257CB5002710F0?OpenDocument&nocache=1" }, "geometry": { "type": "Point", "coordinates": [ 6.6222, 51.4495 ] } },
{ "type": "Feature", "properties": { "Name": "Denkmaltafel 07: Wittfeldsche Heilanstalt", "lat": "51.4499", "lon": "6.6246", "Link": "http:\/\/www.moers.de\/C1257C84004E794D\/html\/0D7CCF4D371EE5EEC1257CB50027F43A?OpenDocument&nocache=1" }, "geometry": { "type": "Point", "coordinates": [ 6.6246, 51.4499 ] } },
{ "type": "Feature", "properties": { "Name": "Geschichtsstation 08: Moers als Kreisstadt", "lat": "51.4501", "lon": "6.6249", "Link": "http:\/\/www.moers.de\/C1257C84004E794D\/html\/90233DCB69875211C1257CB5002B73BF?OpenDocument&nocache=1" }, "geometry": { "type": "Point", "coordinates": [ 6.6249, 51.4501 ] } },
{ "type": "Feature", "properties": { "Name": "Geschichtsstation 09: Moers zur NS-Zeit", "lat": "51.4503", "lon": "6.6252", "Link": "http:\/\/www.moers.de\/C1257C84004E794D\/html\/214A35A7AB22C429C1257CB5002C1E54?OpenDocument&nocache=1" }, "geometry": { "type": "Point", "coordinates": [ 6.6252, 51.4503 ] } },
{ "type": "Feature", "properties": { "Name": "Geschichtsstation 10: Lehrerseminar", "lat": "51.4507", "lon": "6.6265", "Link": "http:\/\/www.moers.de\/C1257C84004E794D\/html\/A7B46F4B8CD64A74C1257CB5002C9FBF?OpenDocument&nocache=1" }, "geometry": { "type": "Point", "coordinates": [ 6.6265, 51.4507 ] } },
{ "type": "Feature", "properties": { "Name": "Geschichtsstation 11: Juden in Moers II", "lat": "51.4513", "lon": "6.6271", "Link": "http:\/\/www.moers.de\/C1257C84004E794D\/html\/14F5C2DCAD6DAA59C1257CB5002D0C34?OpenDocument&nocache=1" }, "geometry": { "type": "Point", "coordinates": [ 6.6271, 51.4513 ] } },
{ "type": "Feature", "properties": { "Name": "Geschichtsstation 12: Juden in Moers I", "lat": "51.4517", "lon": "6.628", "Link": "http:\/\/www.moers.de\/C1257C84004E794D\/html\/28ADA59845894B32C1257CB5002DBD55?OpenDocument&nocache=1" }, "geometry": { "type": "Point", "coordinates": [ 6.628, 51.4517 ] } },
{ "type": "Feature", "properties": { "Name": "Geschichtsstation 13: Neumarkt", "lat": "51.4517", "lon": "6.6253", "Link": "http:\/\/www.moers.de\/C1257C84004E794D\/html\/A78DCDBCF2F19867C1257CB5002E26A1?OpenDocument&nocache=1" }, "geometry": { "type": "Point", "coordinates": [ 6.6253, 51.4517 ] } },
{ "type": "Feature", "properties": { "Name": "Denkmaltafel 14: Peschkenhaus", "lat": "51.4516", "lon": "6.6249", "Link": "http:\/\/www.moers.de\/C1257C84004E794D\/html\/3A576C536E486B2CC1257CB5002FDDDA?OpenDocument&nocache=1" }, "geometry": { "type": "Point", "coordinates": [ 6.6249, 51.4516 ] } },
{ "type": "Feature", "properties": { "Name": "Geschichtsstation 15: Neustadt (Neutor)", "lat": "51.4522", "lon": "6.6232", "Link": "http:\/\/www.moers.de\/C1257C84004E794D\/html\/42BFA6706EAA123CC1257CB500304BDF?OpenDocument&nocache=1" }, "geometry": { "type": "Point", "coordinates": [ 6.6232, 51.4522 ] } },
{ "type": "Feature", "properties": { "Name": "Denkmaltafel 16: Haagstraße 53 -63", "lat": "51.4516", "lon": "6.6231", "Link": "http:\/\/www.moers.de\/C1257C84004E794D\/html\/3B2B0125FCA9A68FC1257CB50030EBAE?OpenDocument&nocache=1" }, "geometry": { "type": "Point", "coordinates": [ 6.6231, 51.4516 ] } },
{ "type": "Feature", "properties": { "Name": "Denkmaltafel 17: Haus Rösgen", "lat": "51.4527", "lon": "6.6265", "Link": "http:\/\/www.moers.de\/C1257C84004E794D\/html\/525D3978F08943D6C1257CB500319EE8?OpenDocument&nocache=1" }, "geometry": { "type": "Point", "coordinates": [ 6.6265, 51.4527 ] } },
{ "type": "Feature", "properties": { "Name": "Geschichtsstation 18: Rathaus", "lat": "51.4533", "lon": "6.6264", "Link": "http:\/\/www.moers.de\/C1257C84004E794D\/html\/58B7B111599B073FC1257CB50031F4FB?OpenDocument&nocache=1" }, "geometry": { "type": "Point", "coordinates": [ 6.6264, 51.4533 ] } },
{ "type": "Feature", "properties": { "Name": "Geschichtsstation 19: Moers als Festungsstadt II", "lat": "51.4539", "lon": "6.625", "Link": "http:\/\/www.moers.de\/C1257C84004E794D\/html\/F97BAAEF740BDF70C1257CB50032D0E4?OpenDocument&nocache=1" }, "geometry": { "type": "Point", "coordinates": [ 6.625, 51.4539 ] } },
{ "type": "Feature", "properties": { "Name": "Geschichtsstation 20: Alt-Moers", "lat": "51.455", "lon": "6.6285", "Link": "http:\/\/www.moers.de\/C1257C84004E794D\/html\/1FFFB67F2299D5B6C1257CB500349641?OpenDocument&nocache=1" }, "geometry": { "type": "Point", "coordinates": [ 6.6285, 51.455 ] } },
{ "type": "Feature", "properties": { "Name": "Geschichtsstation 21: Gymnasium Adolfinum", "lat": "51.4532", "lon": "6.6296", "Link": "http:\/\/www.moers.de\/C1257C84004E794D\/html\/3D4A1625FD480658C1257CB5003526FE?OpenDocument&nocache=1" }, "geometry": { "type": "Point", "coordinates": [ 6.6296, 51.4532 ] } },
{ "type": "Feature", "properties": { "Name": "Geschichtsstation 22: Hanns-Dieter-Hüsch-Bildungszentrum", "lat": "51.453", "lon": "6.6313", "Link": "http:\/\/www.moers.de\/C1257C84004E794D\/html\/425E35FE6399A874C1257CB500422CAC?OpenDocument&nocache=1" }, "geometry": { "type": "Point", "coordinates": [ 6.6313, 51.453 ] } },
{ "type": "Feature", "properties": { "Name": "Denkmaltafel 23: Volksschulen\/Lyzeum", "lat": "51.4494", "lon": "6.6293", "Link": "http:\/\/www.moers.de\/C1257C84004E794D\/html\/31B852FC265EA77BC1257CB500428017?OpenDocument&nocache=1" }, "geometry": { "type": "Point", "coordinates": [ 6.6293, 51.4494 ] } },
{ "type": "Feature", "properties": { "Name": "Geschichtsstation 24: Moers als Festungsstadt III", "lat": "51.4491", "lon": "6.6278", "Link": "http:\/\/www.moers.de\/C1257C84004E794D\/html\/F0A01DD3D382CBCEC1257CB5004366BF?OpenDocument&nocache=1" }, "geometry": { "type": "Point", "coordinates": [ 6.6278, 51.4491 ] } },
{ "type": "Feature", "properties": { "Name": "Geschichtsstation 25: Schlosspark", "lat": "51.4485", "lon": "6.6242", "Link": "http:\/\/www.moers.de\/C1257C84004E794D\/html\/FB78DC1BDC57F294C1257CB500456964?OpenDocument&nocache=1" }, "geometry": { "type": "Point", "coordinates": [ 6.6242, 51.4485 ] } },
{ "type": "Feature", "properties": { "Name": "Geschichtsstation 26: Martinstift", "lat": "51.4417", "lon": "6.6218", "Link": "http:\/\/www.moers.de\/C1257C84004E794D\/html\/9D0BBB5906A823FCC1257CB50045B92C?OpenDocument&nocache=1" }, "geometry": { "type": "Point", "coordinates": [ 6.6218, 51.4417 ] } },
{ "type": "Feature", "properties": { "Name": "Denkmaltafel 27: Vinner Wasserturm", "lat": "51.4403", "lon": "6.6347", "Link": "http:\/\/www.moers.de\/C1257C84004E794D\/html\/E4C7799E93DE3F20C1257CB50046B24B?OpenDocument&nocache=1" }, "geometry": { "type": "Point", "coordinates": [ 6.6347, 51.4403 ] } },
{ "type": "Feature", "properties": { "Name": "Geschichtsstation 28: Naturfreibad Bettenkamp", "lat": "51.4385", "lon": "6.6104", "Link": "http:\/\/www.moers.de\/C1257C84004E794D\/html\/D8BB4AC0014D62EFC1257CB50046F566?OpenDocument&nocache=1" }, "geometry": { "type": "Point", "coordinates": [ 6.6104, 51.4385 ] } },
{ "type": "Feature", "properties": { "Name": "Geschichtsstation 29: Kapellen", "lat": "51.4167", "lon": "6.5944", "Link": "http:\/\/www.moers.de\/C1257C84004E794D\/html\/9BB40D7BA67CDCC5C1257CB500479AEE?OpenDocument&nocache=1" }, "geometry": { "type": "Point", "coordinates": [ 6.5944, 51.4167 ] } },
{ "type": "Feature", "properties": { "Name": "Denkmaltafel 30: Schloss Lauersfort", "lat": "51.4112", "lon": "6.6074", "Link": "http:\/\/www.moers.de\/C1257C84004E794D\/html\/AACDEAED4EE1652DC1257CB50047EA82?OpenDocument&nocache=1" }, "geometry": { "type": "Point", "coordinates": [ 6.6074, 51.4112 ] } },
{ "type": "Feature", "properties": { "Name": "Geschichtsstation 31: Kastell Asciburgium", "lat": "51.4327", "lon": "6.6699", "Link": "http:\/\/www.moers.de\/C1257C84004E794D\/html\/F38AAE181E8B4AB0C1257CB50048B6E9?OpenDocument&nocache=1" }, "geometry": { "type": "Point", "coordinates": [ 6.6699, 51.4327 ] } },
{ "type": "Feature", "properties": { "Name": "Geschichtsstation  32: Mattheck", "lat": "51.4408", "lon": "6.6439", "Link": "http:\/\/www.moers.de\/C1257C84004E794D\/html\/D37DE6E197D09934C1257CB5004A879D?OpenDocument&nocache=1" }, "geometry": { "type": "Point", "coordinates": [ 6.6439, 51.4408 ] } },
{ "type": "Feature", "properties": { "Name": "Denkmaltafel 33: Industriedenkmal Schlachthof", "lat": "51.4483", "lon": "6.6417", "Link": "http:\/\/www.moers.de\/C1257C84004E794D\/html\/24639056DFC33512C1257CB5004D1577?OpenDocument&nocache=1" }, "geometry": { "type": "Point", "coordinates": [ 6.6417, 51.4483 ] } },
{ "type": "Feature", "properties": { "Name": "Denkmaltafel 34: Bahnhof Moers", "lat": "51.4502", "lon": "6.6413", "Link": "http:\/\/www.moers.de\/C1257C84004E794D\/html\/EA6F1415D62852B0C1257CB5004D501B?OpenDocument&nocache=1" }, "geometry": { "type": "Point", "coordinates": [ 6.6413, 51.4502 ] } },
{ "type": "Feature", "properties": { "Name": "Geschichtsstation 35: Friedhof Moers", "lat": "51.4522", "lon": "6.6385", "Link": "http:\/\/www.moers.de\/C1257C84004E794D\/html\/CF7354AAF143D5ACC1257CB5004D9091?OpenDocument&nocache=1" }, "geometry": { "type": "Point", "coordinates": [ 6.6385, 51.4522 ] } },
{ "type": "Feature", "properties": { "Name": "Denkmaltafel 36: Stiftung Bethanien", "lat": "51.461", "lon": "6.634", "Link": "http:\/\/www.moers.de\/C1257C84004E794D\/html\/B4E9A63CE289F7C4C1257CB5004DE710?OpenDocument&nocache=1" }, "geometry": { "type": "Point", "coordinates": [ 6.634, 51.461 ] } },
{ "type": "Feature", "properties": { "Name": "Geschichtsstation 37: Siedlung Meerbeck-Hochstraß", "lat": "51.4595", "lon": "6.6445", "Link": "http:\/\/www.moers.de\/C1257C84004E794D\/html\/759F0D1BB2CB6A5EC1257CB5004E4312?OpenDocument&nocache=1" }, "geometry": { "type": "Point", "coordinates": [ 6.6445, 51.4595 ] } },
{ "type": "Feature", "properties": { "Name": "Geschichtsstation 38: Post in Moers", "lat": "51.4549", "lon": "6.6554", "Link": "http:\/\/www.moers.de\/C1257C84004E794D\/html\/A372231D455B1177C1257CB5004EDDF7?OpenDocument&nocache=1" }, "geometry": { "type": "Point", "coordinates": [ 6.6554, 51.4549 ] } },
{ "type": "Feature", "properties": { "Name": "Geschichtsstation 39: Industriedenkmal Rheinpreußen. Schacht IV", "lat": "51.4546", "lon": "6.6643", "Link": "http:\/\/www.moers.de\/C1257C84004E794D\/html\/86498A5EE8ABF5BDC1257CB5004F4A73?OpenDocument&nocache=1" }, "geometry": { "type": "Point", "coordinates": [ 6.6643, 51.4546 ] } },
{ "type": "Feature", "properties": { "Name": "Geschichtsstation 40: Friedhof Meerbeck", "lat": "51.461", "lon": "6.6453", "Link": "http:\/\/www.moers.de\/C1257C84004E794D\/html\/663E4B828D060DECC1257CB500502DC0?OpenDocument&nocache=1" }, "geometry": { "type": "Point", "coordinates": [ 6.6453, 51.461 ] } },
{ "type": "Feature", "properties": { "Name": "Geschichtsstation 41: Rheinpreußen-Treibstoffwerk", "lat": "51.4698", "lon": "6.6482", "Link": "http:\/\/www.moers.de\/C1257C84004E794D\/html\/5E26D403D3A39323C1257CB60031E4C2?OpenDocument&nocache=1" }, "geometry": { "type": "Point", "coordinates": [ 6.6482, 51.4698 ] } },
{ "type": "Feature", "properties": { "Name": "Geschichtsstation 42: Friedhof Lohmannsheide", "lat": "51.4821", "lon": "6.6627", "Link": "http:\/\/www.moers.de\/C1257C84004E794D\/html\/00519603AF1E0B17C1257CB60032CCA0?OpenDocument&nocache=1" }, "geometry": { "type": "Point", "coordinates": [ 6.6627, 51.4821 ] } },
{ "type": "Feature", "properties": { "Name": "Denkmaltafel 43: Rheinpreußen Schacht V", "lat": "51.4691", "lon": "6.6376", "Link": "http:\/\/www.moers.de\/C1257C84004E794D\/html\/49E9E024417AA876C1257CB600333C7A?OpenDocument&nocache=1" }, "geometry": { "type": "Point", "coordinates": [ 6.6376, 51.4691 ] } },
{ "type": "Feature", "properties": { "Name": "Geschichtsstation 44: Repelen", "lat": "51.4889", "lon": "6.6086", "Link": "http:\/\/www.moers.de\/C1257C84004E794D\/html\/4A5E6233719183C9C1257CB60033AB56?OpenDocument&nocache=1" }, "geometry": { "type": "Point", "coordinates": [ 6.6086, 51.4889 ] } },
{ "type": "Feature", "properties": { "Name": "Geschichtsstation 45: Kurbetrieb Jungborn", "lat": "51.4842", "lon": "6.6056", "Link": "http:\/\/www.moers.de\/C1257C84004E794D\/html\/5EE343ACE8BDBD50C1257CB600341D3C?OpenDocument&nocache=1" }, "geometry": { "type": "Point", "coordinates": [ 6.6056, 51.4842 ] } },
{ "type": "Feature", "properties": { "Name": "Geschichtsstation 46: Siedlung Repelen", "lat": "51.4889", "lon": "6.5871", "Link": "http:\/\/www.moers.de\/C1257C84004E794D\/html\/BE13E4164ABD66C3C1257CB6003488B1?OpenDocument&nocache=1" }, "geometry": { "type": "Point", "coordinates": [ 6.5871, 51.4889 ] } },
{ "type": "Feature", "properties": { "Name": "Geschichtsstation 47: ENNI", "lat": "51.4479", "lon": "6.6319", "Link": "http:\/\/www.moers.de\/C1257C84004E794D\/html\/C30E37B7967CC567C1257CB60034E3A4?OpenDocument&nocache=1" }, "geometry": { "type": "Point", "coordinates": [ 6.6319, 51.4479 ] } }
]
}
